README
ipol.py
setup.py
clipol.egg-info/PKG-INFO
clipol.egg-info/SOURCES.txt
clipol.egg-info/dependency_links.txt
clipol.egg-info/top_level.txt
idl/ace.Dockerfile
idl/bm3d.Dockerfile
idl/dctdenoise.Dockerfile
idl/ffdnet.Dockerfile
idl/lsd.Dockerfile
idl/msdctd.Dockerfile
idl/nlbayes.Dockerfile
idl/nlm.Dockerfile
idl/phs.Dockerfile
idl/scb.Dockerfile
idl/tvdenoise.Dockerfile
idl/tvl1.Dockerfile